nb_output_stripper/__init__.py
nb_output_stripper/__main__.py
nb_output_stripper-0.0.2.dist-info/LICENSE
nb_output_stripper-0.0.2.dist-info/METADATA
nb_output_stripper-0.0.2.dist-info/WHEEL
nb_output_stripper-0.0.2.dist-info/top_level.txt
nb_output_stripper-0.0.2.dist-info/RECORD
