Metadata-Version: 2.1
Name: nb-output-stripper
Version: 0.0.2
Summary: A package that can empty output cells in a notebook by parsing line by line
Author-email: W Vrielink <w.l.j.vrielink@uva.nl>
Classifier: Programming Language :: Python :: 3
Classifier: License :: OSI Approved :: MIT License
Classifier: Operating System :: OS Independent
Requires-Python: >=3.6
License-File: LICENSE
